cli/__init__.py
cli/parser.py
cli/help_texts/conv_create_help.txt
cli/help_texts/conv_delete_help.txt
cli/help_texts/conv_exec_help.txt
cli/help_texts/conv_exec_upload_help.txt
cli/help_texts/conv_get_help.txt
cli/help_texts/conv_list_help.txt
cli/help_texts/conversion_help.txt
cli/help_texts/df_create_help.txt
cli/help_texts/df_create_upload_help.txt
cli/help_texts/df_delete_help.txt
cli/help_texts/df_get_help.txt
cli/help_texts/df_help.txt
cli/help_texts/df_list_help.txt
cli/help_texts/df_trigger_help.txt
cli/help_texts/faascli_general_help.txt
cli/help_texts/login_help.txt
cli/help_texts/sc_create_help.txt
cli/help_texts/sc_delete_help.txt
cli/help_texts/sc_get_help.txt
cli/help_texts/sc_list_help.txt
cli/help_texts/schemasource_help.txt
cli/help_texts/source_connection_help.txt
cli/help_texts/ss_create_help.txt
cli/help_texts/ss_delete_help.txt
cli/help_texts/ss_get_help.txt
cli/help_texts/ss_list_help.txt
cli/help_texts/targetconnection_help.txt
cli/help_texts/tc_create_bigquery_help.txt
cli/help_texts/tc_create_help.txt
cli/help_texts/tc_create_mysql_help.txt
cli/help_texts/tc_create_oracle_help.txt
cli/help_texts/tc_create_postgresql_help.txt
cli/help_texts/tc_create_redshift_help.txt
cli/help_texts/tc_create_s3_help.txt
cli/help_texts/tc_create_snowflake_help.txt
cli/help_texts/tc_create_sqlserver_help.txt
cli/help_texts/tc_delete_help.txt
cli/help_texts/tc_get_help.txt
cli/help_texts/tc_list_help.txt
cli/help_texts/webhook_help.txt
cli/help_texts/wh_create_help.txt
cli/help_texts/wh_delete_help.txt
cli/help_texts/wh_get_help.txt
cli/help_texts/wh_list_help.txt
faas_cli-1.0.4.dist-info/METADATA
faas_cli-1.0.4.dist-info/WHEEL
faas_cli-1.0.4.dist-info/entry_points.txt
faas_cli-1.0.4.dist-info/top_level.txt
faas_cli-1.0.4.dist-info/RECORD
