Metadata-Version: 2.1
Name: faas-cli
Version: 1.0.4
Summary: Command Line Interface (CLI) to work with FaaS API
Home-page: UNKNOWN
Author: Sonra Intelligence Ltd
Author-email: hello@sonra.io
License: UNKNOWN
Platform: UNKNOWN
Classifier: Programming Language :: Python
Classifier: Programming Language :: Python :: 3.6
Classifier: Programming Language :: Python :: 3.7
Classifier: Operating System :: OS Independent
Requires-Python: >=3.6, <4
Requires-Dist: requests (>=2.22.0)
Requires-Dist: colorama (>=0.4.1)
Requires-Dist: PyJWT (==1.7.1)
Requires-Dist: faas-sdk (>=1.0.1)
